Metadata-Version: 2.1
Name: odoo12-addon-agreement-sale
Version: 12.0.1.0.2
Summary: Agreement on sales
Home-page: https://github.com/OCA/contract
Author: Akretion, Odoo Community Association (OCA)
Author-email: support@odoo-community.org
License: AGPL-3
Platform: UNKNOWN
Classifier: Programming Language :: Python
Classifier: Framework :: Odoo
Classifier: Framework :: Odoo :: 12.0
Classifier: License :: OSI Approved :: GNU Affero General Public License v3
Classifier: Development Status :: 4 - Beta
Requires-Python: >=3.5
Requires-Dist: odoo12-addon-agreement-account
Requires-Dist: odoo12-addon-sale-commercial-partner
Requires-Dist: odoo (<12.1dev,>=12.0a)
